pyset_x/__init__.py
pyset_x/core.py
pyset_x-0.0.2.dist-info/LICENSE
pyset_x-0.0.2.dist-info/METADATA
pyset_x-0.0.2.dist-info/WHEEL
pyset_x-0.0.2.dist-info/top_level.txt
pyset_x-0.0.2.dist-info/RECORD
