Metadata-Version: 2.1
Name: pyset-x
Version: 0.0.2
Summary: Like `set -x` in bash
Home-page: https://github.com/czinck/pyset_x
Author: Christian Zinck
Author-email: christian.zinck@gmail.com
License: UNKNOWN
Platform: UNKNOWN
Classifier: Programming Language :: Python :: 3
Classifier: License :: OSI Approved :: MIT License
Classifier: Operating System :: OS Independent
Requires-Python: >=3.0
Requires-Dist: astroid
